LICENSE
MANIFEST.in
README.md
setup.py
pythondata_cpu_microwatt/__init__.py
pythondata_cpu_microwatt.egg-info/PKG-INFO
pythondata_cpu_microwatt.egg-info/SOURCES.txt
pythondata_cpu_microwatt.egg-info/dependency_links.txt
pythondata_cpu_microwatt.egg-info/not-zip-safe
pythondata_cpu_microwatt.egg-info/top_level.txt
pythondata_cpu_microwatt/vhdl/.gitignore
pythondata_cpu_microwatt/vhdl/LICENSE
pythondata_cpu_microwatt/vhdl/Makefile
pythondata_cpu_microwatt/vhdl/README.md
pythondata_cpu_microwatt/vhdl/cache_ram.vhdl
pythondata_cpu_microwatt/vhdl/common.vhdl
pythondata_cpu_microwatt/vhdl/control.vhdl
pythondata_cpu_microwatt/vhdl/core.vhdl
pythondata_cpu_microwatt/vhdl/core_debug.vhdl
pythondata_cpu_microwatt/vhdl/core_dram_tb.vhdl
pythondata_cpu_microwatt/vhdl/core_flash_tb.vhdl
pythondata_cpu_microwatt/vhdl/core_tb.vhdl
pythondata_cpu_microwatt/vhdl/countbits.vhdl
pythondata_cpu_microwatt/vhdl/countbits_tb.vhdl
pythondata_cpu_microwatt/vhdl/cr_file.vhdl
pythondata_cpu_microwatt/vhdl/crhelpers.vhdl
pythondata_cpu_microwatt/vhdl/dcache.vhdl
pythondata_cpu_microwatt/vhdl/dcache_tb.vhdl
pythondata_cpu_microwatt/vhdl/decode1.vhdl
pythondata_cpu_microwatt/vhdl/decode2.vhdl
pythondata_cpu_microwatt/vhdl/decode_types.vhdl
pythondata_cpu_microwatt/vhdl/divider.vhdl
pythondata_cpu_microwatt/vhdl/divider_tb.vhdl
pythondata_cpu_microwatt/vhdl/dmi_dtm_dummy.vhdl
pythondata_cpu_microwatt/vhdl/dmi_dtm_ecp5.vhdl
pythondata_cpu_microwatt/vhdl/dmi_dtm_tb.vhdl
pythondata_cpu_microwatt/vhdl/dmi_dtm_xilinx.vhdl
pythondata_cpu_microwatt/vhdl/dram_tb.vhdl
pythondata_cpu_microwatt/vhdl/execute1.vhdl
pythondata_cpu_microwatt/vhdl/fetch1.vhdl
pythondata_cpu_microwatt/vhdl/foreign_random.vhdl
pythondata_cpu_microwatt/vhdl/fpu.vhdl
pythondata_cpu_microwatt/vhdl/git.vhdl.in
pythondata_cpu_microwatt/vhdl/glibc_random.vhdl
pythondata_cpu_microwatt/vhdl/glibc_random_helpers.vhdl
pythondata_cpu_microwatt/vhdl/gpio.vhdl
pythondata_cpu_microwatt/vhdl/helpers.vhdl
pythondata_cpu_microwatt/vhdl/icache.vhdl
pythondata_cpu_microwatt/vhdl/icache_tb.vhdl
pythondata_cpu_microwatt/vhdl/icache_test.bin
pythondata_cpu_microwatt/vhdl/insn_helpers.vhdl
pythondata_cpu_microwatt/vhdl/loadstore1.vhdl
pythondata_cpu_microwatt/vhdl/logical.vhdl
