Metadata-Version: 2.1
Name: pythondata-cpu-microwatt
Version: 0.0.post1409
Summary: Python module containing vhdl files for microwatt cpu.
Home-page: https://github.com/litex-hub/pythondata-cpu-microwatt
Author: LiteX Authors
Author-email: litex@googlegroups.com
Project-URL: Bug Tracker, https://github.com/litex-hub/pythondata-cpu-microwatt/issues
Project-URL: Source Code, https://github.com/litex-hub/pythondata-cpu-microwatt
Classifier: Programming Language :: Python :: 3
Classifier: License :: OSI Approved
Classifier: Operating System :: OS Independent
Requires-Python: >=3.5
License-File: LICENSE
